{"pceid": "0000", "fmspc": "00606a000000", "tcbLevels": [{"pcesvn": 13, "sgxTcbCompSvnArr": [12, 12, 3, 3, 255, 255, 1, 0, 0, 0, 0, 0, 0, 0, 0, 0], "status": 1}, {"pcesvn": 13, "sgxTcbCompSvnArr": [12, 12, 3, 3, 255, 255, 0, 0, 0, 0, 0, 0, 0, 0, 0, 0], "status": 2}, {"pcesvn": 13, "sgxTcbCompSvnArr": [11, 11, 3, 3, 255, 255, 1, 0, 0, 0, 0, 0, 0, 0, 0, 0], "status": 4}, {"pcesvn": 13, "sgxTcbCompSvnArr": [11, 11, 3, 3, 255, 255, 0, 0, 0, 0, 0, 0, 0, 0, 0, 0], "status": 5}, {"pcesvn": 13, "sgxTcbCompSvnArr": [7, 9, 3, 3, 255, 255, 1, 0, 0, 0, 0, 0, 0, 0, 0, 0], "status": 4}, {"pcesvn": 13, "sgxTcbCompSvnArr": [7, 9, 3, 3, 255, 255, 0, 0, 0, 0, 0, 0, 0, 0, 0, 0], "status": 5}, {"pcesvn": 11, "sgxTcbCompSvnArr": [4, 4, 3, 3, 255, 255, 0, 0, 0, 0, 0, 0, 0, 0, 0, 0], "status": 4}, {"pcesvn": 10, "sgxTcbCompSvnArr": [4, 4, 3, 3, 255, 255, 0, 0, 0, 0, 0, 0, 0, 0, 0, 0], "status": 4}, {"pcesvn": 5, "sgxTcbCompSvnArr": [4, 4, 3, 3, 255, 255, 0, 0, 0, 0, 0, 0, 0, 0, 0, 0], "status": 4}]}